{"keys": ["", "1477048", "1476987"], "data": {"1477048": {"parcel_addr": "314 S Lake Ave", "ogc_fid": 1477048}, "1476987": {"parcel_addr": "Brunswick Rd", "ogc_fid": 1476987}}, "grid": ["      !                                                         ", "                                                                ", "                                                                ", "                                                                ", "               #                                                ", "              ##                                                ", "            ####                                                ", "           #####                                                ", "          ######                                                ", "         #######                                                ", "        #########                                               ", "       ##########                                               ", "      ###########                                               ", "     ############                                               ", "    #############                                               ", "  ###############                                               ", " ################                                               ", "#################                                               ", "#################                                               ", "#################                                               ", "##################                                              ", "##################                                              ", "##################                                              ", "##################                                              ", "##################                                              ", "##################                                              ", "##################                                              ", "##################                                              ", "##################                                              ", "##################                                              ", "###################                                             ", "###################                                             ", "###################                                             ", "###################                                             ", "###################                                             ", "###################                                             ", "###################                                             ", "###################                                             ", "###################                                             ", "###################                                             ", "####################                                            ", "####################                                            ", "####################                                            ", "####################                                            ", "####################                                            ", "####################                                            ", "####################                                            ", "####################                                            ", "####################                                            ", "####################                                            ", "#####################                                           ", "#####################                                           ", "#####################                                           ", "#####################                                           ", "#####################                                           ", "#####################                                           ", "#####################                                           ", "#####################                                           ", "#####################                                           ", "#####################                                           ", "######################                                          ", "######################                                          ", "######################                                          ", "######################                                          "]}