{"keys": ["1479036", "1479039", "1479005", "", "1479064", "1479038", "1479040", "1479037", "1479062", "1479033", "1479041", "1479042", "1479032", "1479043", "1479031", "1479057"], "data": {"1479064": {"parcel_addr": "284 Pawling Ave", "ogc_fid": 1479064}, "1479039": {"parcel_addr": "35 Myrtle Ave", "ogc_fid": 1479039}, "1479038": {"parcel_addr": "25 Myrtle Ave", "ogc_fid": 1479038}, "1479062": {"parcel_addr": "30 Myrtle Ave", "ogc_fid": 1479062}, "1479057": {"parcel_addr": "255 Spring Ave", "ogc_fid": 1479057}, "1479033": {"parcel_addr": "17 Myrtle Ave", "ogc_fid": 1479033}, "1479032": {"parcel_addr": "9 Myrtle Ave", "ogc_fid": 1479032}, "1479031": {"parcel_addr": "5 Myrtle Ave", "ogc_fid": 1479031}, "1479037": {"parcel_addr": "23 Myrtle Ave", "ogc_fid": 1479037}, "1479036": {"parcel_addr": "42 Maple Ave", "ogc_fid": 1479036}, "1479040": {"parcel_addr": "34 Myrtle Ave", "ogc_fid": 1479040}, "1479041": {"parcel_addr": "26 Myrtle Ave", "ogc_fid": 1479041}, "1479005": {"parcel_addr": "41 Myrtle Ave", "ogc_fid": 1479005}, "1479043": {"parcel_addr": "12 Myrtle Ave", "ogc_fid": 1479043}, "1479042": {"parcel_addr": "18 Myrtle Ave", "ogc_fid": 1479042}}, "grid": ["        !!!!!!!!!!!!!!!!!!!!!!!!!###########$$$$$$$$$$%%%%%%%%%%", "       &&&!!!!!!!!!!!!!!!!!!!!!!!!##########$$$$$$$$$$%%%%%%%%%%", "      &&&&&!!!!!!!!!!!!!!!!!!!!!!!!########$$$$$$$$$$%%%%%%%%%%%", "     &&&&&&&!!!!!!!!!!!!!!!!!!!!!!!!!#####$$$$$$$$$$%%%%%%%%%%%%", "    &&&&&&&&&&!!!!!!!!!!!!!!!!!!!!!!!!###$$$$$$$$$$'%%%%%%%%%%%%", "    &&&&&&&&&&&!!!!!!!!!!!!!!!!!!!!!!!!##$$$$$$$$$$''%%%%%%%%%%%", "   &&&&&&&&&&&&&!!!!!!!!!!!!!!!!!!!!!!!!$$$$$$$$$$''''%%%%%%%%%%", "  &&&&&&&&&&&&&&&&!!!!!!!!!!!!!!!!!!!!!$$$$$$$$$$''''''%%%%%%%%%", " &&&&&&&&&&&&&&&&&&!!!!!!!!!!!!!!!!!!!$$$$$$$$$$'''''''''%%%%%%%", " (&&&&&&&&&&&&&&&&&&!!!!!!!!!!!!!!!!!!$$$$$$$$$$''''''''''%%%%%%", "((((&&&&&&&&&&&&&&&&&&!!!!!!!!!!!!!!!$$$$$$$$$$''''''''''''%%%%%", "(((((&&&&&&&&&&&&&&&&&&!!!!!!!!!!!!!$$$$$$$$$$''''''''''''''%%%%", "((((((&&&&&&&&&&&&&&&&&&!!!!!!!!!!!$$$$$$$$$$'''''''''''''''''%%", "(((((((&&&&&&&&&&&&&&&&&&&!!!!!!!!!$$$$$$$$$$''''''''''''''''''%", "(((((((((&&&&&&&&&&&&&&&&&&!!!!!!!$$$$$$$$$$''''''''''''''''''''", "((((((((((&&&&&&&&&&&&&&&&&&!!!!!$$$$$$$$$$'''''''''''''''''''''", "(((((((((((&&&&&&&&&&&&&&&&&&&!!$$$$$$$$$$)))'''''''''''''''''''", "(((((((((((((&&&&&&&&&&&&&&&&&&!$$$$$$$$$$))))''''''''''''''''''", "((((((((((((((&&&&&&&&&&&&&&&&&$$$$$$$$$$))))))'''''''''''''''''", "(((((((((((((((&&&&&&&&&&&&&&&$$$$$$$$$$)))))))))'''''''''''''''", "(((((((((((((((((&&&&&&&&&&&&$$$$$$$$$$)))))))))))''''''''''''''", "((((((((((((((((((&&&&&&&&&&&$$$$$$$$$$))))))))))))'''''''''''''", "(((((((((((((((((((&&&&&&&&&$$$$$$$$$$)))))))))))))))'''''''''''", "*((((((((((((((((((((&&&&&&$$$$$$$$$$)))))))))))))))))''''''''''", "***(((((((((((((((((((&&&&$$$$$$$$$$)))))))))))))))))))'''''''''", "****(((((((((((((((((((&&&$$$$$$$$$$)))))))))))))))))))))'''''''", "*****(((((((((((((((((((&$$$$$$$$$$)))))))))))))))))))))))''''''", "*******((((((((((((((((($$$$$$$$$$+++))))))))))))))))))))))'''''", "********((((((((((((((($$$$$$$$$$+++++)))))))))))))))))))))))'''", "*********(((((((((((((($$$$$$$$$$++++++)))))))))))))))))))))))''", "**********(((((((((((($$$$$$$$$$+++++++++))))))))))))))))))))))'", "************((((((((($$$$$$$$$$+++++++++++))))))))))))))))))))))", "*************((((((($$$$$$$$$$+++++++++++++)))))))))))))))))))))", "**************(((((($$$$$$$$$$+++++++++++++++)))))))))))))))))))", "***************(((($$$$$$$$$$+++++++++++++++++))))))))))))))))))", "*****************($$$$$$$$$$+++++++++++++++++++)))))))))))))))))", "*****************$$$$$$$$$$,+++++++++++++++++++++)))))))))))))))", "*****************$$$$$$$$$$,,+++++++++++++++++++++))))))))))))))", "****************$$$$$$$$$$,,,,+++++++++++++++++++++)))))))))))))", "-**************$$$$$$$$$$,,,,,,,+++++++++++++++++++++)))))))))))", "--************$$$$$$$$$$,,,,,,,,,+++++++++++++++++++++))))))))))", "---***********$$$$$$$$$$,,,,,,,,,,+++++++++++++++++++++)))))))))", "-----********$$$$$$$$$$,,,,,,,,,,,,,+++++++++++++++++++++)))))))", "------******$$$$$$$$$$,,,,,,,,,,,,,,,+++++++++++++++++++++))))))", "-------****$$$$$$$$$$,,,,,,,,,,,,,,,,,+++++++++++++++++++++)))))", "--------***$$$$$$$$$$,,,,,,,,,,,,,,,,,,,+++++++++++++++++++++)))", "----------$$$$$$$$$$,,,,,,,,,,,,,,,,,,,,,+++++++++++++++++++++))", "---------$$$$$$$$$$..,,,,,,,,,,,,,,,,,,,,,+++++++++++++++++++++)", "--------$$$$$$$$$$....,,,,,,,,,,,,,,,,,,,,,,++++++++++++++++++++", "--------$$$$$$$$$$......,,,,,,,,,,,,,,,,,,,,,+++++++++++++++++++", "-------$$$$$$$$$$........,,,,,,,,,,,,,,,,,,,,,++++++++++++++++++", "------$$$$$$$$$$..........,,,,,,,,,,,,,,,,,,,,,,++++++++++++++++", "-----$$$$$$$$$$.............,,,,,,,,,,,,,,,,,,,,,+++++++++++++++", "-----$$$$$$$$$$..............,,,,,,,,,,,,,,,,,,,,,++++++++++++++", "----$$$$$$$$$$................,,,,,,,,,,,,,,,,,,,,,,++++++++++++", "/--$$$$$$$$$$...................,,,,,,,,,,,,,,,,,,,,,++++++++++0", "//$$$$$$$$$$.....................,,,,,,,,,,,,,,,,,,,,,++++++++00", "//$$$$$$$$$$......................,,,,,,,,,,,,,,,,,,,,,,++++++00", "/$$$$$$$$$$........................,,,,,,,,,,,,,,,,,,,,,,++++000", "$$$$$$$$$$...........................,,,,,,,,,,,,,,,,,,,,,++0000", "$$$$$$$$$.............................,,,,,,,,,,,,,,,,,,,,,00000", "$$$$$$$$$..............................,,,,,,,,,,,,,,,,,,,,00000", "$$$$$$$$.................................,,,,,,,,,,,,,,,,,000000", "$$$$$$$...................................,,,,,,,,,,,,,,,0000000"]}