{"keys": ["1479282", "1479297", "1479283", "", "1479287", "1479289", "1479284", "1479198", "1479267", "1479288", "1479199", "1479268", "1479286", "1479201", "1479200", "1479285", "1479202", "1479203", "1479279", "1479278", "1479193", "1479204", "1479208", "1479277"], "data": {"1479288": {"parcel_addr": "33 Heyden Rd", "ogc_fid": 1479288}, "1479289": {"parcel_addr": "30 Heyden Rd", "ogc_fid": 1479289}, "1479282": {"parcel_addr": "41 Heyden Rd", "ogc_fid": 1479282}, "1479283": {"parcel_addr": "37 Heyden Rd", "ogc_fid": 1479283}, "1479284": {"parcel_addr": "35 Heyden Rd", "ogc_fid": 1479284}, "1479285": {"parcel_addr": "49 Wynantskill Way", "ogc_fid": 1479285}, "1479286": {"parcel_addr": "31 Heyden Rd", "ogc_fid": 1479286}, "1479287": {"parcel_addr": "32 Heyden Rd", "ogc_fid": 1479287}, "1479193": {"parcel_addr": "28 Granite Ln", "ogc_fid": 1479193}, "1479198": {"parcel_addr": "28 Heyden Rd", "ogc_fid": 1479198}, "1479199": {"parcel_addr": "26 Heyden Rd", "ogc_fid": 1479199}, "1479279": {"parcel_addr": "51 Wynantskill Way", "ogc_fid": 1479279}, "1479278": {"parcel_addr": "23 Granite Ln", "ogc_fid": 1479278}, "1479277": {"parcel_addr": "53 Wynantskill Way", "ogc_fid": 1479277}, "1479267": {"parcel_addr": "45 Wynantskill Way", "ogc_fid": 1479267}, "1479297": {"parcel_addr": "39 Heyden Rd", "ogc_fid": 1479297}, "1479200": {"parcel_addr": "27 Heyden Rd", "ogc_fid": 1479200}, "1479201": {"parcel_addr": "29 Heyden Rd", "ogc_fid": 1479201}, "1479202": {"parcel_addr": "25 Heyden Rd", "ogc_fid": 1479202}, "1479203": {"parcel_addr": "25 Granite Ln", "ogc_fid": 1479203}, "1479204": {"parcel_addr": "32 Cobblestone Ln", "ogc_fid": 1479204}, "1479208": {"parcel_addr": "21 Granite Ln", "ogc_fid": 1479208}, "1479268": {"parcel_addr": "47 Wynantskill Way", "ogc_fid": 1479268}}, "grid": ["         !!!!!!!!!!#######$$$$$$$$$$%%%%%%%%%%%&&&&&&&&&&&&&&&&&", "        !!!!!!!!!##########$$$$$$$$$$%%%%%%%%%&&&&&&&&&&&&&&&&&&", "        !!!!!!!!############$$$$$$$$$$%%%%%%&&&&&&&&&&&&&&&&&&&&", "        !!!!!!############''$$$$$$$$$$%%%%%&&&&&&&&&&&&&&&&&&&&(", "        !!!!#############''''$$$$$$$$$$%%&&&&&&&&&&&&&&&&&&&&(((", "        !!!############'''''''$$$$$$$$$$&&&&&&&&&&&&&&&&&&&(((((", "        !#############''''''''$$$$$$$$$$&&&&&&&&&&&&&&&&&(((((((", "        ############'''''''''''$$$$$$$$$$&&&&&&&&&&&&&&&((((((((", "       ############'''''''''''''$$$$$$$$$$&&&&&&&&&&&&((((((((((", "))     ##########''''''''''''''*$$$$$$$$$$&&&&&&&&&&((((((((((((", ")))))  #########'''''''''''''****$$$$$$$$$$&&&&&&&((((((((((((((", ")))))))#######''''''''''''''******$$$$$$$$$$&&&&(((((((((((((((+", "))))))))#####'''''''''''''********$$$$$$$$$$&&((((((((((((((((++", ")))))))))##''''''''''''''**********$$$$$$$$$$((((((((((((((((+++", ")))))))))''''''''''''''*************$$$$$$$$$$((((((((((((((++++", "))))))))),''''''''''''**************$$$$$$$$$$(((((((((((((+++++", ")))),,,,,,,'''''''''*****************$$$$$$$$$$(((((((((((++++++", ",,,,,,,,,,,''''''''*****************--$$$$$$$$$$(((((((((+++++++", ",,,,,,,,,,,''''''*****************----$$$$$$$$$$((((((((++++++++", ",,,,,,,,,,,'''''****************-------$$$$$$$$$$((((((+++++++++", ",,,,,,,,,,,,''*****************---------$$$$$$$$$$((((++++++++++", ",,,,,,,,,,,,,****************-----------$$$$$$$$$$(((+++++++++++", ",,,,,,,,,,,,,**************--------------$$$$$$$$$$(++++++++++++", ",,,,,,,,,,,,,,***********----------------.$$$$$$$$$$++++++++++++", ",,,,,,,,,,,,,,,*********---------------...$$$$$$$$$$$$++++++++++", ",,,,,,,,,,,,,,,,******----------------.....$$$$$$$$$$$$$++++++++", ",,,,,,,,,,,,,,,,,,**----------------........$$$$$$$$$$$$$$++++++", ",,,,,,,,,,,,,,,,,,,---------------..........$$$$$$$$$$$$$$$$++++", ",,,,,,,,,,,,,,,,,,,--------------............$$$$$$$$$$$$$$$$$++", ",,,,,,,,,,,,,,,,,,,,-----------.............//$$$$$$$$$$$$$$$$$$", ",,,,,,,,,,,,,,,,,,,,0--------.............//////$$$$$$$$$$$$$$$$", "000000000000000000000-------.............////////$$$$$$$$$$$$$$$", "0000000000000000000000----.............///////////1$$$$$$$$$$$$$", "00000000000000000000000--............////////////11$$$$$$$$$$$$$", "00000000000000000000000.............///////////11111$$$$$$$$$$$$", "000000000000000000000002..........////////////1111111$$$$$$$$$$$", "0000000000000000000000222........///////////111111111$$$$$$$$$$$", "0000000000000000000000222......////////////11111111111$$$$$$$$$$", "00000000000000000000022222....///////////11111111111111$$$$$$$$$", "000000000000000000002222222.////////////11111111111111$$$$$$$$$$", "0000000000000000000022222222//////////11111111111111$$$$$$$$$$$$", "00000000000000000002222222222////////11111111111111$$$$$$$$$$$$$", "00000000000000000022222222222///////1111111111111$$$$$$$$$$$$$$$", "000000000000000002222222222222////11111111111111$$$$$$$$$$$$$$$$", "0000000000000000022222222222222//1111111111111$$$$$$$$$$$$$$$$$$", "000000000000000022222222222222211111111111111$$$$$$$$$$$$$$$$$$$", "3333333300000002222222222222222211111111111$$$$$$$$$$$$$$$$$$$$$", "333333333333332222222222222222222111111111$$$$$$$$$$$$$$$$$$$$$$", "3333333333333322222222222222222221111111$$$$$$$$$$$$$$$$$$$$$$$$", "333333333333322222222222222222222211111$$$$$$$$$$$$$$$$$$$$$$$$$", "3333333333334222222222222222222222211$$$$$$$$$$$$$$$$$$$$$$$$$$5", "333333333334442222222222222222222221$$$$$$$$$$$$$$$$$$$$$$$$$555", "333333333334444422222222222222222222$$$$$$$$$$$$$$$$$$$$$$$55555", "3333333333444444422222222222222222222$$$$$$$$$$$$$$$$$$$$$555555", "3333333334444444442222222222222222222$$$$$$$$$$$$$$$$$$$66555555", "33333333444444444444222222222222222222$$$$$$$$$$$$$$$$6666555555", "33333333444444444444422222222222222222$$$$$$$$$$$$$$$66666655555", "333333344444444444444422222222222222$$$$$$$$$$$$$$$6666666655555", "33333344444444444444444422222222222$$$$$$$$$$$$$$666666666665555", "3333337444444444444444444222222222$$$$$$$$$$$$$$6666666666666555", "833337774444444444444444442222222$$$$$$$$$$$$$666666666666666555", "88887777744444444444444444442222$$$$$$$$$$$$66666666666666666655", "8887777777744444444444444444422$$$$$$$$$$$$666666666666666666655", "8887777777774444444444444444442$$$$$$$$$$$6666666666666666666665"]}