{"keys": ["", "1469085", "1469087", "1469086", "1469084", "1469088", "1469083", "1469141", "1469082", "1469142"], "data": {"1469142": {"parcel_addr": "550 First Ave", "ogc_fid": 1469142}, "1469141": {"parcel_addr": "554 First Ave", "ogc_fid": 1469141}, "1469088": {"parcel_addr": "562 First Ave", "ogc_fid": 1469088}, "1469087": {"parcel_addr": "First Ave", "ogc_fid": 1469087}, "1469086": {"parcel_addr": "First Ave", "ogc_fid": 1469086}, "1469085": {"parcel_addr": "577-579 First Ave", "ogc_fid": 1469085}, "1469084": {"parcel_addr": "First Ave", "ogc_fid": 1469084}, "1469083": {"parcel_addr": "First Ave", "ogc_fid": 1469083}, "1469082": {"parcel_addr": "537-545 First Ave", "ogc_fid": 1469082}}, "grid": ["                                                            !!!!", "                                                            !!!!", "                                                            !!!!", "                                                           !!!!!", "                                                           !!!!!", "                                                           !!!!!", "                                                          !!!!!!", "                                                          !!!!!!", "                                                          !!!!!!", "                                                             !!!", "                                                                ", "                                                                ", "                                                                ", "                                                                ", "                                                                ", "                                                                ", "                                                                ", "                                                                ", "                                                                ", "                                                                ", "                                                      ####      ", "                                                      #######   ", "                                                     ########   ", "                                                    #########   ", "                                                    #########   ", "                                                    ########    ", "                                                    ########    ", "                                                   #########    ", "                                                   ########     ", "                                                   ########     ", "                                                  #########     ", "                                                  ########      ", "                                                 #########      ", "                                                 #########      ", "                                                 ########       ", "                                                #########       ", "                                                $$#######       ", "                                                %$$$$$##        ", "                                               %%%%%$$$$        ", "                                               %%%%%%%%$        ", "                                              %%%%%%%%%         ", "                                              %%%%%%%%%         ", "                                             %%%%%%%%%%        &", "                                             %%%%%%%%%         &", "                                            '''%%%%%%%         (", "                                            ''''''%%%%        ((", "                                            '''''''''         ((", "                                           ''''''''''         ((", "                                           ''''''''''        (((", "                                           '''''''''         (((", "                                          ''''''''''         (((", "                                         '''''''''''        ((((", "                                        '''''''''''         ((((", "                                       ))''''''''''         ((((", "                                       )))))'''''''        (((((", "                                      )))))))))'''         *((((", "                                     )))))))))))))         *****", "                                    ))))))))))))))        ******", "                                   ))))))))))))))         ******", "                                  )))))))))))))))         ******", "                                 ))))))))))))))))        *******", "                                ))))))))))))))))         *******", "                                ))))))))))))))))         *******", "                               )))))))))))))))))        ********"]}