{"keys": ["1476066", "", "1471144", "1471141", "1471142", "1471140"], "data": {"1476066": {"parcel_addr": "Campbell Ave", "ogc_fid": 1476066}, "1471144": {"parcel_addr": "126 Campbell Ave", "ogc_fid": 1471144}, "1471142": {"parcel_addr": "63 Ballina St", "ogc_fid": 1471142}, "1471141": {"parcel_addr": "59 Donegal Ave", "ogc_fid": 1471141}, "1471140": {"parcel_addr": "61 Ballina St", "ogc_fid": 1471140}}, "grid": ["     !!!!!!!!!!!!!!!!!!!!!!#############################!!!!!!!!", "  !!!!!!!!!!!!!!!!!!!!!!!################################!!!!!!!", "!!!!!!!!!!!!!!!!!!!!!!!##################################!!!!!!!", "!!!!!!!!!!!!!!!!!!!!!!###################################!!!!!!!", "!!!!!!!!!!!!!!!!!!!!#####################################!!!!!!!", "!!!!!!!!!!!!!!!!!!#######################################!!!!!!!", "!!!!!!!!!!!!!!!!!#########################################!!!!!!", "!!!!!!!!!!!!!!!###########################################!!!!!!", "!!!!!!!!!!!!!#############################################!!!!!!", "!!!!!!!!!!!!##############################################!!!!!!", "!!!!!!!!!!################################################!!!!!!", "!!!!!!!!###################################################!!!!!", "!!!!!!!####################################################!!!!!", "!!!!!######################################################!!!!!", "!!!########################################################!!!!!", "!##########################################################!!!!!", "############################################################!!!!", "############################################################!!!!", "############################################################!!!!", "############################################################!!!!", "############################################################!!!!", "############################################################!!!!", "#############################################################!!!", "#############################################################!!!", "#############################################################!!!", "#############################################################!!!", "#############################################################!!!", "##############################################################!!", "##############################################################!!", "##############################################################!!", "##############################################################!!", "##############################################################!!", "###############################################################!", "###############################################################!", "###############################################################!", "###############################################################!", "###############################################################!", "###############################################################!", "###############################################################$", "#############################################################$$$", "############################################################$$$$", "##########################################################$$$$$$", "#########################################################$$$$$$$", "#######################################################$$$$$$$$$", "######################################################$$$$$$$$$$", "#####################################################$$$$$$$$$$$", "###################################################$$$$$$$$$$$$$", "##################################################$$$$$$$$$$$$$$", "################################################$$$$$$$$$$$$$$$$", "###############################################$$$$$$$$$$$$$$$$$", "#############################################$$$$$$$$$$$$$$$$$$$", "############################################%$$$$$$$$$$$$$$$$$$$", "##########################################%%%$$$$$$$$$$$$$$$$$$$", "#########################################%%%%%$$$$$$$$$$$$$$$$$$", "#######################################%%%%%%%%$$$$$$$$$$$$$$$$$", "######################################%%%%%%%%%$$$$$$$$$$$$$$$$$", "#####################################%%%%%%%%%%%$$$$$$$$$$$$$$$$", "###################################%%%%%%%%%%%%%%$$$$$$$$$$$$$$$", "##################################%%%%%%%%%%%%%%%$$$$$$$$$$$$$$$", "################################%%%%%%%%%%%%%%%%%%$$$$$$$$$$$$$!", "###############################%%%%%%%%%%%%%%%%%%%%$$$$$$$$$$$!!", "#############################&&&&%%%%%%%%%%%%%%%%%%$$$$$$$$$!!!!", "############################&&&&&&%%%%%%%%%%%%%%%%%%$$$$$$$!!!!!", "##########################&&&&&&&&&%%%%%%%%%%%%%%%%%%$$$$!!!!!!!"]}