{"keys": ["1470209", "", "1470206", "1472143", "1470205", "1472155", "1470201", "1470200", "1470199", "1470207"], "data": {"1472155": {"parcel_addr": "1 Regatta Pl", "ogc_fid": 1472155}, "1472143": {"parcel_addr": "1-6 Bond St", "ogc_fid": 1472143}, "1470207": {"parcel_addr": "895 River St", "ogc_fid": 1470207}, "1470206": {"parcel_addr": "17 Second Ave", "ogc_fid": 1470206}, "1470205": {"parcel_addr": "909 River St", "ogc_fid": 1470205}, "1470209": {"parcel_addr": "21 Second Ave", "ogc_fid": 1470209}, "1470201": {"parcel_addr": "907 River St", "ogc_fid": 1470201}, "1470200": {"parcel_addr": "903 River St", "ogc_fid": 1470200}, "1470199": {"parcel_addr": "899 River St", "ogc_fid": 1470199}}, "grid": ["                                                            !!!!", "                                                            !!!!", "########                                                    !!!!", "#################                                           !!!!", "##########################                                  !!!!", "####################################                        !!!!", "#############################################               !!!!", "######################################################      !!!!", "############################################################!!!!", "############################################################!!!!", "############################################################!!!!", "############################################################!!!!", "############################################################!!!!", "$$$#########################################################!!!!", "$$$$%%%#####################################################!!!!", "$$$%%%%%%%%%%%%%%###########################################!!!!", "$$$%%%%%%%%%%%%%%%%%%%%%%%##################################!!!!", "$$%%%%%%%%%%%%%%%%%%%%%%%%%%%%%%%%%#########################!!!!", "$$%%%%%%%%%%%%%%%%%%%%%%%%%%%%%%%%%%%%%%%%%%################!!!!", "$$%%%%%%%%%%%%%%%%%%%%%%%%%%%%%%%%%%%%%%%%%%%%%%%%%%%#######!!!!", "$%%%%%%%%%%%%%%%%%%%%%%%%%%%%%%%%%%%%%%%%%%%%%%%%%%%%%%%%%%%!!!!", "$%%%%%%%%%%%%%%%%%%%%%%%%%%%%%%%%%%%%%%%%%%%%%%%%%%%%%%%%%%%!!!!", "%%%%%%%%%%%%%%%%%%%%%%%%%%%%%%%%%%%%%%%%%%%%%%%%%%%%%%%%%%%%!!!!", "%%%%%%%%%%%%%%%%%%%%%%%%%%%%%%%%%%%%%%%%%%%%%%%%%%%%%%%%%%%%!!!!", "%%%%%%%%%%%%%%%%%%%%%%%%%%%%%%%%%%%%%%%%%%%%%%%%%%%%%%%%%%%%!!!!", "%%%%%%%%%%%%%%%%%%%%%%%%%%%%%%%%%%%%%%%%%%%%%%%%%%%%%%%%%%%%!!!!", "%%%%%%%%%%%%%%%%%%%%%%%%%%%%%%%%%%%%%%%%%%%%%%%%%%%%%%%%%%%%!!!!", "%%%%%%%%%%%%%%%%%%%%%%%%%%%%%%%%%%%%%%%%%%%%%%%%%%%%%%%%%%%%!!!!", "%%%%%%%%%%%%%%%%%%%%%%%%%%%%%%%%%%%%%%%%%%%%%%%%%%%%%%%%%%%%!!!!", "%%%%%%%%%%%%%%%%%%%%%%%%%%%%%%%%%%%%%%%%%%%%%%%%%%%%%%%%%%%%!!!!", "%%%%%%%%%%%%%%%%%%%%%%%%%%%%%%%%%%%%%%%%%%%%%%%%%%%%%%%%%%%%!!!!", "%%%%%%%%%%%%%%%%%%%%%%%%%%%%%%%%%%%%%%%%%%%%%%%%%%%%%%%%%%%%!!!!", "%%%%%%%%%%%%%%%%%%%%%%%%%%%%%%%%%%%%%%%%%%%%%%%%%%%%%%%%%%%%!!!!", "%%%%%%%%%%%%%%%%%%%%%%%%%%%%%%%%%%%%%%%%%%%%%%%%%%%%%%%%%%%%!!!!", "%%%%%%%%%%%%%%%%%%%%%%%%%%%%%%%%%%%%%%%%%%%%%%%%%%%%%%%%%%%%!!!!", "%%%%%%%%%%%%%%%%%%%%%%%%%%%%%%%%%%%%%%%%%%%%%%%%%%%%%%%%%%%%%!!!", "$%%%%%%%%%%%%%%%%%%%%%%%%%%%%%%%%%%%%%%%%%%%%%%%%%%%%%%%%%%%%!!!", "$&&&&&&%%%%%%%%%%%%%%%%%%%%%%%%%%%%%%%%%%%%%%%%%%%%%%%%%%%%%%!!!", "$$&&&&&&&&&&&&%%%%%%%%%%%%%%%%%%%%%%%%%%%%%%%%%%%%%%%%%%%%%%%!!!", "$$&&&&&&&&&&&&&&&&&&&&%%%%%%%%%%%%%%%%%%%%%%%%%%%%%%%%%%%%%%%!!!", "$$$&&&&&&&&&&&&&&&&&&&&&&&&&&&%%%%%%%%%%%%%%%%%%%%%%%%%%%%%%%!!!", "$$$&&&&&&&&&&&&&&&&&&&&&&&&&&&&&&&&&&&%%%%%%%%%%%%%%%%%%%%%%%!!!", "$$$$&&&&&&&&&&&&&&&&&&&&&&&&&&&&&&&&&&&&'''''''%%%%%%%%%%%%%%!!!", "$$$$&&&&&&&&&&&&&&&&&&&&&&&&&&&&&&&&&&&&'''''''''''''''%%%%%%!!!", "$$$$$&&&&&&&&&&&&&&&&&&&&&&&&&&&&&&&&&&&'''''''''''''''''''''!!!", "$$$$$&&&&&&&&&&&&&&&&&&&&&&&&&&&&&&&&&&&'''''''''''''''''''''!!!", "$$$$$$&&&&&&&&&&&&&&&&&&&&&&&&&&&&&&&&&&'''''''''''''''''''''!!!", "$$$$$$&&&&&&&&&&&&&&&&&&&&&&&&&&&&&&&&&&'''''''''''''''''''''!!!", "$$$$$$$&&&&&&&&&&&&&&&&&&&&&&&&&&&&&&&&&'''''''''''''''''''''!!!", "$$$$$$$&&&&&&&&&&&&&&&&&&&&&&&&&&&&&&&&&'''''''''''''''''''''!!!", "$$$$$$$&&&&&&&&&&&&&&&&&&&&&&&&&&&&&&&&&(((((((('''''''''''''!!!", "$$$$$$$&&&&&&&&&&&&&&&&&&&&&&&&&&&&&&&&&(((((((((((((((((''''!!!", "$$$$$$$&&&&&&&&&&&&&&&&&&&&&&&&&&&&&&&&&(((((((((((((((((((((!!!", "$$$$$$$&&&&&&&&&&&&&&&&&&&&&&&&&&&&&&&&&(((((((((((((((((((((!!!", "$$$$$$$&&&&&&&&&&&&&&&&&&&&&&&&&&&&&&&&&))))(((((((((((((((((!!!", "$$$$$$$&&&&&&&&&&&&&&&&&&&&&&&&&&&&&&&&&)))))))))))))((((((((!!!", "$$$$$$$&&&&&&&&&&&&&&&&&&&&&&&&&&&&&&&&&)))))))))))))))))))))!!!", "$$$$$$$&&&&&&&&&&&&&&&&&&&&&&&&&&&&&&&&&)))))))))))))))))))))!!!", "$$$$$$$&&&&&&&&&&&&&&&&&&&&&&&&&&&&&&&&&)))))))))))))))))))))!!!", "$$$$$$$&&&&&&&&&&&&&&&&&&&&&&&&&&&&&&&&&)))))))))))))))))))))!!!", "$$$$$$$&&&&&&&&&&&&&&&&&&&&&&&&&&&&&&&&&)))))))))))))))))))))!!!", "$$$$$$$&&&&&&&&&&&&&&&&&&&&&&&&&&&&&&&&&)))))))))))))))))))))!!!", "$$$$$$$&&&&&&&&&&&&&&&&&&&&&&&&&&&&&&&&&)))))))))))))))))))))!!!", "$$$$$$$&&&&&&&&&&&&&&&&&&&&&&&&&&&&&&&&&**********)))))))))))!!!"]}