{"keys": ["1467439", "", "1467425"], "data": {"1467425": {"parcel_addr": "Highpointe Dr", "ogc_fid": 1467425}, "1467439": {"parcel_addr": "1-28 Stoneledge Dr", "ogc_fid": 1467439}}, "grid": ["                             !!!!###############################", "                              !!!!##############################", "                              !!!!!#############################", "                               !!!!#############################", "                               !!!!!############################", "                                !!!!############################", "                                 !!!!###########################", "                                 !!!!!##########################", "                                  !!!!!#########################", "                                  !!!!!#########################", "                                   !!!!!########################", "                                    !!!!!#######################", "                                     !!!!!######################", "                                      !!!!!#####################", "                                       !!!!!####################", "                                        !!!!!###################", "                                         !!!!!##################", "                                          !!!!!#################", "                                           !!!!!################", "                                            !!!!!###############", "                                             !!!!!##############", "                                              !!!!!#############", "                                               !!!!!############", "                                                !!!!!###########", "                                                 !!!!!##########", "                                                 !!!!!!#########", "                                                  !!!!!!########", "                                                   !!!!!!#######", "                                                    !!!!!!######", "                                                     !!!!!!#####", "                                                      !!!!!!####", "                                                       !!!!!!###", "                                                        !!!!!!##", "                                                         !!!!!!#", "                                                          !!!!!!", "                                                           !!!!!", "                                                            !!!!", "                                                             !!!", "                                                              !!", "                                                               !", "                                                                ", "                                                                ", "                                                                ", "                                                                ", "                                                                ", "                                                                ", "                                                                ", "                                                                ", "                                                                ", "                                                                ", "                                                                ", "                                                                ", "                                                                ", "                                                                ", "                                                                ", "                                                                ", "                                                                ", "                                                                ", "                                                                ", "                                                                ", "                                                                ", "                                                                ", "                                                                ", "                                                                "]}