{"keys": ["1476165", "1476167", "1476166", "1476171", "", "1476117", "1476168"], "data": {"1476168": {"parcel_addr": "86 Spring Ave", "ogc_fid": 1476168}, "1476117": {"parcel_addr": "Spring Ave", "ogc_fid": 1476117}, "1476171": {"parcel_addr": "12 Whitman Ct", "ogc_fid": 1476171}, "1476165": {"parcel_addr": "Spring Ave (North Of)", "ogc_fid": 1476165}, "1476166": {"parcel_addr": "Spring Ave", "ogc_fid": 1476166}, "1476167": {"parcel_addr": "10 Westover Rd", "ogc_fid": 1476167}}, "grid": ["                                                        !!!!!!!!", "                                                        !!!!!!!!", "#                                                       !!!!!!!!", "#                                                       !!!!!!!!", "##                                                      !!!!!!!!", "###                                                     !!!!!!!!", "####                                                    !!!!!!!!", "#####                                                   !!!!!!!!", "######                                                  !!!!!!!!", "######                                                  !!!!!!!!", "#######                                                 !!!!!!!!", "########                                                !!!!!!!!", "#########                                               !!!!!!!!", "##########                                              !!!!!!!!", "###########                                             !!!!!!!!", "###########                                             !!!!!!!!", "############                                            !!!!!!!!", "############                                            !!!!!!!!", "#############                                           !!!!!!!!", "#############                                           !!!!!!!!", "##############                                          !!!!!!!!", "##############                                           !!!!!!!", "##############                                           !!!!!!!", "###############                                          !!!!!!!", "###############                                          !!!!!!!", "################                                         !!!!!!!", "################               ###                       !!!!!!!", "#################            ########                    !!!!!!!", "#################          #############                 !!!!!!!", "##################       ##################              !!!!!!$", "%%################     #######################           !!!!!$$", "%%%%##############   ############################        !!!!$$$", "%%%%%%##############################################     !!$$$$$", "%%%%%%%%###############################################  !$$$$$$", "%%%%%%%%%%%###############################################$$$$$$", "%%%%%%%%%%%%%##############################################$$$$$", "%%%%%%%%%%%%%%%##############################################$$$", "%%%%%%%%%%%%%%%%%#############################################$$", "%%%%%%%%%%%%%%%%%%%#############################################", "%%%%%%%%%%%%%%%%%%%%%###########################################", "%%%%%%%%%%%%%%%%%%%%%%%#########################################", "&&%%%%%%%%%%%%%%%%%%%%%%%%######################################", "&&&&%%%%%%%%%%%%%%%%%%%%%%%%####################################", "&&&'''%%%%%%%%%%%%%%%%%%%%%%%%##################################", "&&&'''''%%%%%%%%%%%%%%%%%%%%%%%%################################", "&&&''''''''%%%%%%%%%%%%%%%%%%%%%%%##############################", "&&'''''''''&&%%%%%%%%%%%%%%%%%%%%%%%############################", "&&'''''''''&&&&%%%%%%%%%%%%%%%%%%%%%%%##########################", "&'''''''''&&&&&&&%%%%%%%%%%%%%%%%%%%%%%%########################", "&'''''''''&&&&&&&&&%%%%%%%%%%%%%%%%%%%%%%%%#####################", "'''''''''&&&&&&&&&&&&%%%%%%%%%%%%%%%%%%%%%%%%###################", "'''''''''&&&&&&&&&&&&&&%%%%%%%%%%%%%%%%%%%%%%%%#################", "''''''''&&&&&&&&&&&&&&&&&%%%%%%%%%%%%%%%%%%%%%%%%###############", "''''''''&&&&&&&&&&&&&&&&&&&%%%%%%%%%%%%%%%%%%%%%%%%#############", "''''''''&&&&&&&&&&&&&&&&&&&&&&%%%%%%%%%%%%%%%%%%%%%%%###########", "'''''''&&&&&&&&&&&&&&&&&&&&&&&&&%%%%%%%%%%%%%%%%%%%%%%##########", "'''''''&&&&&&&&&&&&&&&&&&&&&&&&&&&%%%%%%%%%%%%%%%%%%%%%%########", "''''''&&&&&&&&&&&&&&&&&&&&&&&&&&&&&&%%%%%%%%%%%%%%%%%%%%%%######", "''''''&&&&&&&&&&&&&&&&&&&&&&&&&&&&&&&&%%%%%%%%%%%%%%%%%%%%%#####", "'''''&&&&&&&&&&&&&&&&&&&&&&&&&&&&&&&&&&&%%%%%%%%%%%%%%%%%%%%%###", "'''''&&&&&&&&&&&&&&&&&&&&&&&&&&&&&&&&&&&&&%%%%%%%%%%%%%%%%%%%%##", "''''&&&&&&&&&&&&&&&&&&&&&&&&&&&&&&&&&&&&&&&&%%%%%%%%%%%%%%%%%%%#", "''''&&&&&&&&&&&&&&&&&&&&&&&&&&&&&&&&&&&&&&&&&&%%%%%%%%%%%%%%%%%%", "'''&&&&&&&&&&&&&&&&&&&&&&&&&&&&&&&&&&&&&&&&&&&&&%%%%%%%%%%%%%%%%"]}