{"keys": ["", "1474134", "1474135", "1474136"], "data": {"1474135": {"parcel_addr": "39 Front St", "ogc_fid": 1474135}, "1474134": {"parcel_addr": "43 Washington St", "ogc_fid": 1474134}, "1474136": {"parcel_addr": "27 River St", "ogc_fid": 1474136}}, "grid": ["                                 !!!!!!!!!!!################### ", "                                 !!!!!!!!!!#################### ", "                                 !!!!!!!!!!#################### ", "                                !!!!!!!!!!!###################  ", "                                !!!!!!!!!!!###################  ", "                                !!!!!!!!!!!###################  ", "                                !!!!!!!!!!####################  ", "                                !!!!!!!!!!####################  ", "                               !!!!!!!!!!!####################  ", "                               !!!!!!!!!!!####################  ", "                               !!!!!!!!!!####################   ", "                               !!!!!!!!!!####################   ", "                              !!!!!!!!!!!####################   ", "                              !!!!!!!!!!!####################   ", "                              !!!!!!!!!!!####################   ", "                              !!!!!!!!!!#####################   ", "                             !!!!!!!!!!!####################    ", "                             !!!!!!!!!!!####################    ", "                             !!!!!!!!!!!####################    ", "                             !!!!!!!!!!#####################    ", "                             !!!!!!!!!!#####################    ", "                            !!!!!!!!!!!#####################    ", "                            !!!!!!!!!!!#####################    ", "                            !!!!!!!!!!!####################     ", "                            !!!!!!!!!!#####################     ", "                           !!!!!!!!!!!#####################     ", "                           !!!!!!!!!!!#####################     ", "                           !!!!!!!!!!!#####################     ", "                           !!!!!!!!!!######################     ", "                           !!!!!!!!!!#####################      ", "                          !!!!!!!!!!!#####################      ", "                          !!!!!!!!!!!#####################      ", "                          !!!!!!!!!!!#####################      ", "                          !!!!!!!!!!######################      ", "                         !!!!!!!!!!!######################      ", "                         !!!!!!!!!!!######################      ", "                         !!!!!!!!!!!#####################       ", "                         !!!!!!!!!!######################       ", "                         !!!!!!!!!!######################       ", "                        !!!!!!!!!!!######################       ", "                        !!!!!!!!!!!######################       ", "                        !!!!!!!!!!!######################       ", "                        !!!!!!!!!!######################        ", "                       !!!!!!!!!!!######################        ", "                       !!!!!!!!!!!######################        ", "                       !!!!!!!!!!!######################        ", "                       !!!!!!!!!!#######################        ", "                      !!!!!!!!!!!#######################        ", "                      !!!!!!!!!!!#######################        ", "                      !!!!!!!!!!!######################         ", "                      !!!!!!!!!!!######################         ", "                      !!!!!!!!!!#######################        $", "                     !!!!!!!!!!!#######################        $", "                     !!!!!!!!!!!#######################        $", "                     !!!!!!!!!!!#######################        $", "                     !!!!!!!!!!#######################         $", "                    !!!!!!!!!!!#######################         $", "                    !!!!!!!!!!!#######################        $$", "                    !!!!!!!!!!!#######################        $$", "                    !!!!!!!!!!!#######################        $$", "                    !!!!!!!!!!########################        $$", "                   !!!!!!!!!!!########################        $$", "                   !!!!!!!!!!!#######################         $$", "                   !!!!!!!!!!!#######################         $$"]}