{"keys": ["1478393", "", "1466564"], "data": {"1466564": {"parcel_addr": "163 Oakwood Ave", "ogc_fid": 1466564}, "1478393": {"parcel_addr": "160 Oakwood Ave", "ogc_fid": 1478393}}, "grid": ["                 !!!!!!!!!!!!!!!################################", "                !!!!!!!!!!!!!!!#################################", "               !!!!!!!!!!!!!!!##################################", "              !!!!!!!!!!!!!!!###################################", "             !!!!!!!!!!!!!!!####################################", "            !!!!!!!!!!!!!!!!####################################", "           !!!!!!!!!!!!!!!!#####################################", "          !!!!!!!!!!!!!!!!######################################", "         !!!!!!!!!!!!!!!!#######################################", "        !!!!!!!!!!!!!!!!########################################", "!!     !!!!!!!!!!!!!!!!#########################################", "!!!!  !!!!!!!!!!!!!!!!##########################################", "!!!!!!!!!!!!!!!!!!!!!###########################################", "!!!!!!!!!!!!!!!!!!!!############################################", "!!!!!!!!!!!!!!!!!!!#############################################", "!!!!!!!!!!!!!!!!!!##############################################", "!!!!!!!!!!!!!!!!!###############################################", "!!!!!!!!!!!!!!!!################################################", "!!!!!!!!!!!!!!!#################################################", "!!!!!!!!!!!!!!##################################################", "!!!!!!!!!!!!!###################################################", "!!!!!!!!!!!!####################################################", "!!!!!!!!!!!#####################################################", "!!!!!!!!!!######################################################", "!!!!!!!!!#######################################################", "!!!!!!!!########################################################", "!!!!!!!#########################################################", "!!!!!!##########################################################", "!!!!!###########################################################", "!!!!############################################################", "!!!#############################################################", "!!##############################################################", "!###############################################################", "################################################################", "################################################################", "################################################################", "################################################################", "################################################################", "################################################################", "################################################################", "################################################################", "################################################################", "################################################################", "################################################################", "################################################################", "################################################################", "################################################################", "################################################################", "################################################################", "################################################################", "################################################################", "################################################################", "################################################################", "################################################################", "################################################################", "################################################################", "################################################################", "################################################################", "################################################################", "################################################################", "################################################################", "################################################################", "################################################################", "!!##############################################################"]}